llama_index/tools/parallel_web_systems/__init__.py
llama_index/tools/parallel_web_systems/base.py
llama_index_tools_parallel_web_systems-0.1.0.dist-info/METADATA
llama_index_tools_parallel_web_systems-0.1.0.dist-info/WHEEL
llama_index_tools_parallel_web_systems-0.1.0.dist-info/licenses/LICENSE
llama_index_tools_parallel_web_systems-0.1.0.dist-info/RECORD
