Metadata-Version: 2.4
Name: llama-index-tools-parallel-web-systems
Version: 0.1.0
Summary: LlamaIndex integration for Parallel AI Search and Extract APIs
Author-email: Your Name <you@example.com>
License-Expression: MIT
License-File: LICENSE
Requires-Python: <4.0,>=3.9
Requires-Dist: httpx>=0.24.0
Requires-Dist: llama-index-core<0.15,>=0.13.0
